mydiabby_client/__init__.py
mydiabby_client/client.py
mydiabby_client/exceptions.py
mydiabby_client/utils.py
mydiabby_client-0.1.2.dist-info/licenses/LICENSE
mydiabby_client-0.1.2.dist-info/METADATA
mydiabby_client-0.1.2.dist-info/WHEEL
mydiabby_client-0.1.2.dist-info/top_level.txt
mydiabby_client-0.1.2.dist-info/RECORD
