Metadata-Version: 2.4
Name: mydiabby-client
Version: 0.1.2
Summary: API Client to access pump and CGM data
Author-email: Noah Fontaine <noah.fontaine.uk@gmail.com>
License: MIT License
Project-URL: Homepage, https://github.com/NoahFontaine/mydiabby-client
Project-URL: Issues, https://github.com/NoahFontaine/mydiabby-client/issues
Requires-Python: >=3.12
License-File: LICENSE
Requires-Dist: requests>=2.32.5
Dynamic: license-file
